aioaquarea/__init__.py
aioaquarea/api_client.py
aioaquarea/auth.py
aioaquarea/const.py
aioaquarea/consumption_manager.py
aioaquarea/core.py
aioaquarea/data.py
aioaquarea/decorators.py
aioaquarea/device_control.py
aioaquarea/device_manager.py
aioaquarea/entities.py
aioaquarea/errors.py
aioaquarea/statistics.py
aioaquarea/util.py
aioaquarea-1.0.3.dist-info/licenses/LICENSE
aioaquarea-1.0.3.dist-info/METADATA
aioaquarea-1.0.3.dist-info/WHEEL
aioaquarea-1.0.3.dist-info/top_level.txt
aioaquarea-1.0.3.dist-info/RECORD
