Metadata-Version: 2.4
Name: aioaquarea
Version: 1.0.3
Summary: Asynchronous library to control Panasonic Aquarea devices
Author-email: "Carlos J. Aliaga" <dev@cjaliaga.net>
License: MIT License
Project-URL: Homepage, https://github.com/cjaliaga/aioaquarea
Project-URL: Bug Tracker, https://github.com/cjaliaga/aioaquarea/issues
Classifier: Programming Language :: Python :: 3
Classifier: License :: OSI Approved :: MIT License
Classifier: Operating System :: OS Independent
Requires-Python: >=3.9
License-File: LICENSE
Requires-Dist: aiohttp
Requires-Dist: StrEnum; python_version < "3.11"
Requires-Dist: bs4
Dynamic: license-file
